ejad/__init__.py
ejad/cli.py
ejad/gemini_integration.py
ejad/static_issue.py
ejd-0.1.11.dist-info/licenses/LICENSE
ejd-0.1.11.dist-info/METADATA
ejd-0.1.11.dist-info/WHEEL
ejd-0.1.11.dist-info/entry_points.txt
ejd-0.1.11.dist-info/top_level.txt
ejd-0.1.11.dist-info/RECORD
