Metadata-Version: 2.4
Name: ejd
Version: 0.1.11
License-File: LICENSE
Requires-Dist: google-generativeai>=0.3.0
Requires-Dist: python-dotenv>=1.0.0
Dynamic: license-file
Dynamic: requires-dist
